[
  {
    "level": "INTERMEDIO",
    "id": "45c9116c-7c6f-4e51-9574-ba92b32f3411",
    "name": "Gustavo",
    "lastName": "Alvarez",
    "dni": "24989790",
    "email": "gustavo.alvarez@domain.com"
  },
  {
    "level": "PRINCIPIANTE",
    "id": "23797507-2467-4d7e-8a6d-2c5aa6483e37",
    "name": "Miguel",
    "lastName": "Vargas",
    "dni": "10405547",
    "email": "miguel.vargas@service.com"
  },
  {
    "level": "INTERMEDIO",
    "id": "711cf0b5-0e5d-45fb-8677-10c37ab3f50e",
    "name": "Sandra",
    "lastName": "Mora",
    "dni": "21530074",
    "email": "sandra.mora@icloud.com"
  },
  {
    "level": "PRINCIPIANTE",
    "id": "b74bf611-2f4e-4ac9-8a63-d87c06464ce5",
    "name": "Luis",
    "lastName": "Santana",
    "dni": "35182015",
    "email": "luis.santana@mailbox.org"
  },
  {
    "level": "AVANZADO",
    "id": "be56c435-c63a-4711-bdc5-1712b6e0159e",
    "name": "Vladimir",
    "lastName": "Vega",
    "dni": "69592724",
    "email": "vladimir.vega@gmx.com"
  },
  {
    "level": "INTERMEDIO",
    "id": "328d843a-8558-41ec-9400-8191551921c4",
    "name": "Miguel",
    "lastName": "Herrera",
    "dni": "91357895",
    "email": "miguel.herrera@provider.com"
  },
  {
    "level": "INTERMEDIO",
    "id": "74519f41-7fa0-40db-ab3c-b3c6001413db",
    "name": "Alfonso",
    "lastName": "Peña",
    "dni": "71328941",
    "email": "alfonso.peña@laposte.net"
  },
  {
    "level": "PRINCIPIANTE",
    "id": "03b3c0a8-e37f-48a7-a9e8-e4cc1aa81c1d",
    "name": "Liliana",
    "lastName": "Martinez",
    "dni": "21109686",
    "email": "liliana.martinez@hotmail.com"
  },
  {
    "level": "AVANZADO",
    "id": "fadac0d3-3b6a-4c14-ac64-afd2a8fe1a56",
    "name": "Esteban",
    "lastName": "Villalobos",
    "dni": "84863749",
    "email": "esteban.villalobos@zohomail.com"
  },
  {
    "level": "PRINCIPIANTE",
    "id": "ceb344c6-6aff-4378-9077-1a58e222e266",
    "name": "Victoria",
    "lastName": "Diaz",
    "dni": "92557787",
    "email": "victoria.diaz@live.com"
  }
]